odoo/addons/fetchmail_notify_error_to_sender_test/README.rst
odoo/addons/fetchmail_notify_error_to_sender_test/__init__.py
odoo/addons/fetchmail_notify_error_to_sender_test/__manifest__.py
odoo/addons/fetchmail_notify_error_to_sender_test/i18n/ca.po
odoo/addons/fetchmail_notify_error_to_sender_test/i18n/fetchmail_notify_error_to_sender_test.pot
odoo/addons/fetchmail_notify_error_to_sender_test/i18n/it.po
odoo/addons/fetchmail_notify_error_to_sender_test/readme/CONTRIBUTORS.md
odoo/addons/fetchmail_notify_error_to_sender_test/readme/DESCRIPTION.md
odoo/addons/fetchmail_notify_error_to_sender_test/static/description/icon.png
odoo/addons/fetchmail_notify_error_to_sender_test/static/description/index.html
odoo/addons/fetchmail_notify_error_to_sender_test/tests/__init__.py
odoo/addons/fetchmail_notify_error_to_sender_test/tests/test_fetchmail_notify_error_to_sender.py
odoo_addon_fetchmail_notify_error_to_sender_test-17.0.1.0.0.4.dist-info/METADATA
odoo_addon_fetchmail_notify_error_to_sender_test-17.0.1.0.0.4.dist-info/WHEEL
odoo_addon_fetchmail_notify_error_to_sender_test-17.0.1.0.0.4.dist-info/top_level.txt
odoo_addon_fetchmail_notify_error_to_sender_test-17.0.1.0.0.4.dist-info/RECORD
