Metadata-Version: 2.1
Name: odoo-addon-fetchmail_notify_error_to_sender_test
Version: 17.0.1.0.0.4
Requires-Python: >=3.10
Requires-Dist: odoo-addon-fetchmail_notify_error_to_sender>=17.0dev,<17.1dev
Requires-Dist: odoo>=17.0a,<17.1dev
Summary: Test for Fetchmail Notify Error to Sender
Home-page: https://github.com/OCA/server-tools
License: AGPL-3
Author: Agile Business Group,ForgeFlow,Odoo Community Association (OCA)
Author-email: support@odoo-community.org
Classifier: Programming Language :: Python
Classifier: Framework :: Odoo
Classifier: Framework :: Odoo :: 17.0
Classifier: License :: OSI Approved :: GNU Affero General Public License v3
